quart_openapi/__about__.py
quart_openapi/__init__.py
quart_openapi/cors.py
quart_openapi/marshmallow.py
quart_openapi/pint.py
quart_openapi/resource.py
quart_openapi/swagger.py
quart_openapi/typing.py
quart_openapi/utils.py
quart_openapi-1.7.2.dist-info/LICENSE.txt
quart_openapi-1.7.2.dist-info/METADATA
quart_openapi-1.7.2.dist-info/WHEEL
quart_openapi-1.7.2.dist-info/top_level.txt
quart_openapi-1.7.2.dist-info/RECORD
