Metadata-Version: 2.1
Name: quart-openapi
Version: 1.7.2
Summary: Framework for Quart to add swagger generation to routes and restful resources
Home-page: https://github.com/factset/quart-openapi
Author: Matt Topol
Author-email: mtopol@factset.com
License: Apache 2.0
Keywords: quart swagger api rest openapi flask
Platform: UNKNOWN
Classifier: License :: OSI Approved :: Apache Software License
Classifier: Programming Language :: Python :: 3.6
Classifier: Programming Language :: Python :: 3
Classifier: Programming Language :: Python
Classifier: Operating System :: OS Independent
Classifier: Intended Audience :: Developers
Classifier: Environment :: Web Environment
Classifier: Topic :: Internet :: WWW/HTTP :: Dynamic Content
Classifier: Topic :: Software Development :: Libraries :: Python Modules
Requires-Python: >=3.7
License-File: LICENSE.txt
Requires-Dist: jsonschema (>=3.0.0)
Requires-Dist: werkzeug (>=1.0.0)
Requires-Dist: quart (>=0.12.0) ; python_version >= "3.7"
Provides-Extra: doc
Requires-Dist: Sphinx (==1.7.2) ; extra == 'doc'
Requires-Dist: sphinx-autodoc-typehints (>=1.3.0) ; extra == 'doc'
Requires-Dist: alabaster (>=0.7.10) ; extra == 'doc'
